README.txt
setup.cfg
setup.py
docs/HISTORY.txt
docs/INSTALL.txt
docs/LICENSE.GPL
docs/LICENSE.txt
easyshop/__init__.py
easyshop.groups.egg-info/PKG-INFO
easyshop.groups.egg-info/SOURCES.txt
easyshop.groups.egg-info/dependency_links.txt
easyshop.groups.egg-info/entry_points.txt
easyshop.groups.egg-info/namespace_packages.txt
easyshop.groups.egg-info/not-zip-safe
easyshop.groups.egg-info/requires.txt
easyshop.groups.egg-info/top_level.txt
easyshop/groups/__init__.py
easyshop/groups/configure.zcml
easyshop/groups/profiles.zcml
easyshop/groups/tests.py
easyshop/groups/adapters/__init__.py
easyshop/groups/adapters/configure.zcml
easyshop/groups/adapters/group_management.py
easyshop/groups/adapters/product_management.py
easyshop/groups/browser/__init__.py
easyshop/groups/browser/configure.zcml
easyshop/groups/browser/group_view.pt
easyshop/groups/browser/group_view.py
easyshop/groups/browser/groups_view.pt
easyshop/groups/browser/groups_view.py
easyshop/groups/content/__init__.py
easyshop/groups/content/containers.py
easyshop/groups/content/group.py
easyshop/groups/profiles/__init__.py
easyshop/groups/profiles/default/factorytool.xml
easyshop/groups/profiles/default/types.xml
easyshop/groups/profiles/default/workflows.xml
easyshop/groups/profiles/default/types/GroupsContainer.xml
easyshop/groups/profiles/default/types/ProductGroup.xml